Metadata-Version: 2.1
Name: xarray-stac
Version: 0.0.21b0
Summary: UNKNOWN
Home-page: https://github.com/M3nin0/xarray-stac
Author: Felipe Carlos
Author-email: felipe.carlos@inpe.br
License: MIT
Keywords: STAC,datacube,xarray
Platform: any
Classifier: Development Status :: 3 - Alpha
Classifier: Environment :: Console
Classifier: Environment :: Console :: Curses  
Classifier: Intended Audience :: Education
Classifier: Intended Audience :: Science/Research
Classifier: Intended Audience :: Developers
Classifier: License :: OSI Approved :: MIT License
Classifier: Operating System :: OS Independent
Classifier: Programming Language :: Python :: 3 :: Only
Classifier: Topic :: Scientific/Engineering :: GIS
Classifier: Topic :: Software Development :: Libraries :: Python Modules
Classifier: Topic :: Utilities
Provides-Extra: all
